alethiometer/__init__.py
alethiometer/__version__.py
alethiometer/utils.py
alethiometer/zc_proxy.py
alethiometer/datasets/__init__.py
alethiometer/datasets/dataset.py
alethiometer/datasets/h5py_dataset.py
alethiometer/datasets/imagenet16.py
alethiometer/zero_cost_metrics/__init__.py
alethiometer/zero_cost_metrics/grad_norm.py
alethiometer/zero_cost_metrics/grasp.py
alethiometer/zero_cost_metrics/naswot.py
alethiometer/zero_cost_metrics/naswot_relu.py
alethiometer/zero_cost_metrics/ntk.py
alethiometer/zero_cost_metrics/snip.py
alethiometer/zero_cost_metrics/synflow.py
alethiometer/zero_cost_metrics/t_cet.py
alethiometer/zero_cost_metrics/tenas.py
alethiometer/zero_cost_metrics/zen.py
alethiometer/zero_cost_metrics/zico.py
alethiometer-1.1.2.dist-info/LICENSE
alethiometer-1.1.2.dist-info/METADATA
alethiometer-1.1.2.dist-info/WHEEL
alethiometer-1.1.2.dist-info/top_level.txt
alethiometer-1.1.2.dist-info/RECORD
