Metadata-Version: 2.1
Name: alethiometer
Version: 1.1.2
Summary: ZC proxies calculation repo, altered from foresight package.
Home-page: https://github.com/iViolinSolo/zero-cost-proxies
Author: ViolinSolo
Author-email: i.violinsolo@gmail.com
License: Apache Software License
Classifier: License :: OSI Approved :: Apache Software License
Classifier: Programming Language :: Python
Classifier: Programming Language :: Python :: 3
Classifier: Programming Language :: Python :: 3.6
Classifier: Programming Language :: Python :: Implementation :: CPython
Classifier: Programming Language :: Python :: Implementation :: PyPy
Requires-Python: >=3.6.0
License-File: LICENSE
Requires-Dist: h5py (>=2.10.0)
Requires-Dist: numpy (>=1.18.4)
Requires-Dist: Pillow (>=4)
